Database.py
_wasp.cpython-38-x86_64-linux-gnu.so
wasp.py
ornl_wasp-4.3.0.dist-info/METADATA
ornl_wasp-4.3.0.dist-info/WHEEL
ornl_wasp-4.3.0.dist-info/top_level.txt
ornl_wasp-4.3.0.dist-info/RECORD
