Metadata-Version: 2.1
Name: ornl-wasp
Version: 4.3.0
Summary: Workbench Analysis Sequence Processor 4.3.0
Home-page: https://code.ornl.gov/neams-workbench/wasp
Author: Shane Henderson, Robert A. Lefebvre, Brandon R. Langley
Author-email: hendersonsc@ornl.gov, lefebvrera@ornl.gov
